pyreka/__init__.py
pyreka-1.0.1.dist-info/METADATA
pyreka-1.0.1.dist-info/WHEEL
pyreka-1.0.1.dist-info/entry_points.txt
pyreka-1.0.1.dist-info/top_level.txt
pyreka-1.0.1.dist-info/RECORD
