Metadata-Version: 2.1
Name: pyreka
Version: 1.0.1
Summary: Package for finding python functions in codebases and environment packages
Author-email: George Allaway <george.w.allaway@gmail.com>
Project-URL: Homepage, https://github.com/Allaway11/pyreka
Project-URL: Bug Tracker, https://github.com/Allaway11/pyreka/issues
Keywords: search,functions,finder
Classifier: Programming Language :: Python
Classifier: Programming Language :: Python :: 3
Classifier: License :: OSI Approved :: MIT License
Classifier: Operating System :: OS Independent
Requires-Python: >=3.10
Requires-Dist: rich (==12.6.0)
Requires-Dist: typer (==0.7.0)
